wslm/__init__.py
wslm/decorators.py
wslm/util.py
wslm/windows_command.py
wslm/wslm.py
wslm-1.0.1.dist-info/entry_points.txt
wslm-1.0.1.dist-info/LICENSE
wslm-1.0.1.dist-info/WHEEL
wslm-1.0.1.dist-info/METADATA
wslm-1.0.1.dist-info/RECORD
